{
  "gameId": 3931,
  "showNumber": "2864",
  "title": "Show #2864 - Thursday, January 30, 1997",
  "date": "1997-01-30",
  "comments": "",
  "contestants": [
    "Davia",
    "Ellen",
    "Rick"
  ],
  "rounds": {
    "jeopardy": {
      "categories": [
        "LITERATURE",
        "TELEVISION",
        "TRANSPORTATION",
        "GENERAL SCIENCE",
        "FOOTWEAR",
        "'80s WORDS & PHRASES"
      ],
      "clues": [
        {
          "category": "TELEVISION",
          "value": 100,
          "clue": "His sitcom is admittedly about \"nothing\", just little things people experience but never see on TV",
          "answer": "Seinfeld",
          "isDailyDouble": false,
          "orderNumber": 1,
          "correctContestants": [
            "Davia"
          ],
          "incorrectContestants": [],
          "wasTripleStumper": false,
          "runningScores": [
            {
              "player": "Davia",
              "score": 100
            },
            {
              "player": "Ellen",
              "score": 0
            },
            {
              "player": "Rick",
              "score": 0
            }
          ]
        },
        {
          "category": "TELEVISION",
          "value": 200,
          "clue": "This Will Smith sitcom ended its 6-year run in 1996",
          "answer": "The Fresh Prince of Bel-Air",
          "isDailyDouble": false,
          "orderNumber": 2,
          "correctContestants": [
            "Rick"
          ],
          "incorrectContestants": [],
          "wasTripleStumper": false,
          "runningScores": [
            {
              "player": "Davia",
              "score": 100
            },
            {
              "player": "Ellen",
              "score": 0
            },
            {
              "player": "Rick",
              "score": 200
            }
          ]
        },
        {
          "category": "TELEVISION",
          "value": 300,
          "clue": "This sitcom ended the 1995-96 season with Jamie discovering she's finally pregnant",
          "answer": "Mad About You",
          "isDailyDouble": false,
          "orderNumber": 3,
          "correctContestants": [
            "Davia"
          ],
          "incorrectContestants": [],
          "wasTripleStumper": false,
          "runningScores": [
            {
              "player": "Davia",
              "score": 400
            },
            {
              "player": "Ellen",
              "score": 0
            },
            {
              "player": "Rick",
              "score": 200
            }
          ]
        },
        {
          "category": "TELEVISION",
          "value": 400,
          "clue": "When it returned in June of '96 with Raquel Welch & Gerald McRaney, it was retitled \"CPW\"",
          "answer": "Central Park West",
          "isDailyDouble": false,
          "orderNumber": 4,
          "correctContestants": [
            "Ellen"
          ],
          "incorrectContestants": [],
          "wasTripleStumper": false,
          "runningScores": [
            {
              "player": "Davia",
              "score": 400
            },
            {
              "player": "Ellen",
              "score": 400
            },
            {
              "player": "Rick",
              "score": 200
            }
          ]
        },
        {
          "category": "LITERATURE",
          "value": 100,
          "clue": "Some say Cervantes wrote a portion of this 1605 novel in jail",
          "answer": "Don Quixote",
          "isDailyDouble": false,
          "orderNumber": 5,
          "correctContestants": [
            "Ellen"
          ],
          "incorrectContestants": [],
          "wasTripleStumper": false,
          "runningScores": [
            {
              "player": "Davia",
              "score": 400
            },
            {
              "player": "Ellen",
              "score": 500
            },
            {
              "player": "Rick",
              "score": 200
            }
          ]
        },
        {
          "category": "LITERATURE",
          "value": 200,
          "clue": "This commander of the Nautilus was actually an Indian prince named Dakkar",
          "answer": "Captain Nemo",
          "isDailyDouble": false,
          "orderNumber": 6,
          "correctContestants": [
            "Ellen"
          ],
          "incorrectContestants": [],
          "wasTripleStumper": false,
          "runningScores": [
            {
              "player": "Davia",
              "score": 400
            },
            {
              "player": "Ellen",
              "score": 700
            },
            {
              "player": "Rick",
              "score": 200
            }
          ]
        },
        {
          "category": "LITERATURE",
          "value": 300,
          "clue": "In an Edward Lear poem, the owl & the pussycat go to sea in a boat of this color",
          "answer": "pea green",
          "isDailyDouble": false,
          "orderNumber": 7,
          "correctContestants": [
            "Davia"
          ],
          "incorrectContestants": [],
          "wasTripleStumper": false,
          "runningScores": [
            {
              "player": "Davia",
              "score": 700
            },
            {
              "player": "Ellen",
              "score": 700
            },
            {
              "player": "Rick",
              "score": 200
            }
          ]
        },
        {
          "category": "TELEVISION",
          "value": 500,
          "clue": "Late '60s undercover police unit made up of Pete Cochrane, Linc Hayes & Julie Barnes",
          "answer": "The Mod Squad",
          "isDailyDouble": false,
          "orderNumber": 8,
          "correctContestants": [
            "Davia"
          ],
          "incorrectContestants": [],
          "wasTripleStumper": false,
          "runningScores": [
            {
              "player": "Davia",
              "score": 1200
            },
            {
              "player": "Ellen",
              "score": 700
            },
            {
              "player": "Rick",
              "score": 200
            }
          ]
        },
        {
          "category": "LITERATURE",
          "value": 400,
          "clue": "Aunt Chloe is his wife & Arthur Shelby is his master in Kentucky",
          "answer": "Uncle Tom",
          "isDailyDouble": false,
          "orderNumber": 9,
          "correctContestants": [
            "Rick"
          ],
          "incorrectContestants": [],
          "wasTripleStumper": false,
          "runningScores": [
            {
              "player": "Davia",
              "score": 1200
            },
            {
              "player": "Ellen",
              "score": 700
            },
            {
              "player": "Rick",
              "score": 600
            }
          ]
        },
        {
          "category": "LITERATURE",
          "value": 500,
          "clue": "Harry Haller is the title character of this Herman Hesse novel",
          "answer": "Steppenwolf",
          "isDailyDouble": false,
          "orderNumber": 10,
          "correctContestants": [],
          "incorrectContestants": [
            "Rick"
          ],
          "wasTripleStumper": true,
          "runningScores": [
            {
              "player": "Davia",
              "score": 1200
            },
            {
              "player": "Ellen",
              "score": 700
            },
            {
              "player": "Rick",
              "score": 100
            }
          ]
        },
        {
          "category": "FOOTWEAR",
          "value": 100,
          "clue": "These slip-ons make \"cents\", as each shoe has a slot for a coin",
          "answer": "penny loafer",
          "isDailyDouble": false,
          "orderNumber": 11,
          "correctContestants": [
            "Davia"
          ],
          "incorrectContestants": [],
          "wasTripleStumper": false,
          "runningScores": [
            {
              "player": "Davia",
              "score": 1300
            },
            {
              "player": "Ellen",
              "score": 700
            },
            {
              "player": "Rick",
              "score": 100
            }
          ]
        },
        {
          "category": "GENERAL SCIENCE",
          "value": 100,
          "clue": "The 16th letter of the Greek alphabet; in math it has the approximate value of 3.14",
          "answer": "pi",
          "isDailyDouble": false,
          "orderNumber": 12,
          "correctContestants": [
            "Davia"
          ],
          "incorrectContestants": [],
          "wasTripleStumper": false,
          "runningScores": [
            {
              "player": "Davia",
              "score": 1400
            },
            {
              "player": "Ellen",
              "score": 700
            },
            {
              "player": "Rick",
              "score": 100
            }
          ]
        },
        {
          "category": "GENERAL SCIENCE",
          "value": 200,
          "clue": "A lens that curves inward is concave & one that curves outward is this type",
          "answer": "convex",
          "isDailyDouble": false,
          "orderNumber": 13,
          "correctContestants": [
            "Davia"
          ],
          "incorrectContestants": [],
          "wasTripleStumper": false,
          "runningScores": [
            {
              "player": "Davia",
              "score": 1600
            },
            {
              "player": "Ellen",
              "score": 700
            },
            {
              "player": "Rick",
              "score": 100
            }
          ]
        },
        {
          "category": "GENERAL SCIENCE",
          "value": 300,
          "clue": "This wax obtained from sheep wool is composed largely of cholesterol esters",
          "answer": "lanolin",
          "isDailyDouble": false,
          "orderNumber": 14,
          "correctContestants": [
            "Ellen"
          ],
          "incorrectContestants": [],
          "wasTripleStumper": false,
          "runningScores": [
            {
              "player": "Davia",
              "score": 1600
            },
            {
              "player": "Ellen",
              "score": 1000
            },
            {
              "player": "Rick",
              "score": 100
            }
          ]
        },
        {
          "category": "GENERAL SCIENCE",
          "value": 400,
          "clue": "Highly flammable & once used for photographic film, it was the first commercial synthetic plastic",
          "answer": "celluloid",
          "isDailyDouble": false,
          "orderNumber": 15,
          "correctContestants": [],
          "incorrectContestants": [],
          "wasTripleStumper": true,
          "runningScores": [
            {
              "player": "Davia",
              "score": 1600
            },
            {
              "player": "Ellen",
              "score": 1000
            },
            {
              "player": "Rick",
              "score": 100
            }
          ]
        },
        {
          "category": "GENERAL SCIENCE",
          "value": 500,
          "clue": "Emeralds & aquamarines are forms of this mineral",
          "answer": "beryl",
          "isDailyDouble": false,
          "orderNumber": 16,
          "correctContestants": [],
          "incorrectContestants": [
            "Ellen",
            "Rick"
          ],
          "wasTripleStumper": true,
          "runningScores": [
            {
              "player": "Davia",
              "score": 1600
            },
            {
              "player": "Ellen",
              "score": 500
            },
            {
              "player": "Rick",
              "score": -400
            }
          ]
        },
        {
          "category": "FOOTWEAR",
          "value": 200,
          "clue": "It's a heavy low-heeled shoe or an Irish accent",
          "answer": "brogue",
          "isDailyDouble": false,
          "orderNumber": 17,
          "correctContestants": [
            "Ellen"
          ],
          "incorrectContestants": [],
          "wasTripleStumper": false,
          "runningScores": [
            {
              "player": "Davia",
              "score": 1600
            },
            {
              "player": "Ellen",
              "score": 700
            },
            {
              "player": "Rick",
              "score": -400
            }
          ]
        },
        {
          "category": "FOOTWEAR",
          "value": 300,
          "clue": "These racquet-shaped frames allow the wearer to walk without sinking, if you get our drift",
          "answer": "snowshoes",
          "isDailyDouble": false,
          "orderNumber": 18,
          "correctContestants": [
            "Ellen"
          ],
          "incorrectContestants": [],
          "wasTripleStumper": false,
          "runningScores": [
            {
              "player": "Davia",
              "score": 1600
            },
            {
              "player": "Ellen",
              "score": 1000
            },
            {
              "player": "Rick",
              "score": -400
            }
          ]
        },
        {
          "category": "FOOTWEAR",
          "value": 400,
          "clue": "This soft leather shoe's name goes back to Virginia Algonquian",
          "answer": "moccasin",
          "isDailyDouble": false,
          "orderNumber": 19,
          "correctContestants": [
            "Ellen"
          ],
          "incorrectContestants": [],
          "wasTripleStumper": false,
          "runningScores": [
            {
              "player": "Davia",
              "score": 1600
            },
            {
              "player": "Ellen",
              "score": 1400
            },
            {
              "player": "Rick",
              "score": -400
            }
          ]
        },
        {
          "category": "FOOTWEAR",
          "value": 500,
          "clue": "What Witt wears when working",
          "answer": "ice skates",
          "isDailyDouble": false,
          "orderNumber": 20,
          "correctContestants": [
            "Rick"
          ],
          "incorrectContestants": [],
          "wasTripleStumper": false,
          "runningScores": [
            {
              "player": "Davia",
              "score": 1600
            },
            {
              "player": "Ellen",
              "score": 1400
            },
            {
              "player": "Rick",
              "score": 100
            }
          ]
        },
        {
          "category": "'80s WORDS & PHRASES",
          "value": 100,
          "clue": "Japanese for \"empty orchestra\", this device allows you to sing along with Mitch-san",
          "answer": "karaoke",
          "isDailyDouble": false,
          "orderNumber": 21,
          "correctContestants": [
            "Ellen"
          ],
          "incorrectContestants": [],
          "wasTripleStumper": false,
          "runningScores": [
            {
              "player": "Davia",
              "score": 1600
            },
            {
              "player": "Ellen",
              "score": 1500
            },
            {
              "player": "Rick",
              "score": 100
            }
          ]
        },
        {
          "category": "'80s WORDS & PHRASES",
          "value": 200,
          "clue": "This term for selling goods by phone dates to the 1980s",
          "answer": "telemarketing",
          "isDailyDouble": false,
          "orderNumber": 22,
          "correctContestants": [
            "Ellen"
          ],
          "incorrectContestants": [],
          "wasTripleStumper": false,
          "runningScores": [
            {
              "player": "Davia",
              "score": 1600
            },
            {
              "player": "Ellen",
              "score": 1700
            },
            {
              "player": "Rick",
              "score": 100
            }
          ]
        },
        {
          "category": "'80s WORDS & PHRASES",
          "value": 300,
          "clue": "Political aides who put a positive slant on an event or the group who sang \"Two Princes\"",
          "answer": "Spin Doctors",
          "isDailyDouble": false,
          "orderNumber": 23,
          "correctContestants": [
            "Ellen"
          ],
          "incorrectContestants": [],
          "wasTripleStumper": false,
          "runningScores": [
            {
              "player": "Davia",
              "score": 1600
            },
            {
              "player": "Ellen",
              "score": 2000
            },
            {
              "player": "Rick",
              "score": 100
            }
          ]
        },
        {
          "category": "'80s WORDS & PHRASES",
          "value": 700,
          "clue": "It's the 2-word \"clear barrier\" keeping women from promotion into upper management",
          "answer": "glass ceiling",
          "isDailyDouble": true,
          "orderNumber": 24,
          "correctContestants": [
            "Ellen"
          ],
          "incorrectContestants": [],
          "wasTripleStumper": false,
          "runningScores": [
            {
              "player": "Davia",
              "score": 1600
            },
            {
              "player": "Ellen",
              "score": 2700
            },
            {
              "player": "Rick",
              "score": 100
            }
          ]
        },
        {
          "category": "'80s WORDS & PHRASES",
          "value": 500,
          "clue": "In 1986 Americans learned 2 Russian words: glasnost, meaning \"openness\", & this, meaning \"restructuring\"",
          "answer": "perestroika",
          "isDailyDouble": false,
          "orderNumber": 25,
          "correctContestants": [
            "Ellen"
          ],
          "incorrectContestants": [],
          "wasTripleStumper": false,
          "runningScores": [
            {
              "player": "Davia",
              "score": 1600
            },
            {
              "player": "Ellen",
              "score": 3200
            },
            {
              "player": "Rick",
              "score": 100
            }
          ]
        },
        {
          "category": "TRANSPORTATION",
          "value": 100,
          "clue": "These engineless aircraft have longer & narrower wings than powered aircraft",
          "answer": "gliders",
          "isDailyDouble": false,
          "orderNumber": 26,
          "correctContestants": [
            "Ellen"
          ],
          "incorrectContestants": [],
          "wasTripleStumper": false,
          "runningScores": [
            {
              "player": "Davia",
              "score": 1600
            },
            {
              "player": "Ellen",
              "score": 3300
            },
            {
              "player": "Rick",
              "score": 100
            }
          ]
        },
        {
          "category": "TRANSPORTATION",
          "value": 200,
          "clue": "Formerly, team members on these vehicles would lean back & snap forward in unison, \"bobbing\"",
          "answer": "bobsled",
          "isDailyDouble": false,
          "orderNumber": 27,
          "correctContestants": [
            "Ellen"
          ],
          "incorrectContestants": [
            "Rick"
          ],
          "wasTripleStumper": false,
          "runningScores": [
            {
              "player": "Davia",
              "score": 1600
            },
            {
              "player": "Ellen",
              "score": 3500
            },
            {
              "player": "Rick",
              "score": -100
            }
          ]
        },
        {
          "category": "TRANSPORTATION",
          "value": 300,
          "clue": "Term for the one-wheeled passenger carrier attached to a motorcycle",
          "answer": "sidecar",
          "isDailyDouble": false,
          "orderNumber": 28,
          "correctContestants": [
            "Ellen"
          ],
          "incorrectContestants": [],
          "wasTripleStumper": false,
          "runningScores": [
            {
              "player": "Davia",
              "score": 1600
            },
            {
              "player": "Ellen",
              "score": 3800
            },
            {
              "player": "Rick",
              "score": -100
            }
          ]
        },
        {
          "category": "TRANSPORTATION",
          "value": 400,
          "clue": "This, the most prestigious bicycle race, takes 25-30 days to complete",
          "answer": "Tour de France",
          "isDailyDouble": false,
          "orderNumber": 29,
          "correctContestants": [
            "Ellen"
          ],
          "incorrectContestants": [],
          "wasTripleStumper": false,
          "runningScores": [
            {
              "player": "Davia",
              "score": 1600
            },
            {
              "player": "Ellen",
              "score": 4200
            },
            {
              "player": "Rick",
              "score": -100
            }
          ]
        },
        {
          "category": "TRANSPORTATION",
          "value": 500,
          "clue": "These vehicles named for a Pennsylvania region had a freight capacity of about 6 metric tons",
          "answer": "Conestoga wagons",
          "isDailyDouble": false,
          "orderNumber": 30,
          "correctContestants": [
            "Davia"
          ],
          "incorrectContestants": [],
          "wasTripleStumper": false,
          "runningScores": [
            {
              "player": "Davia",
              "score": 2100
            },
            {
              "player": "Ellen",
              "score": 4200
            },
            {
              "player": "Rick",
              "score": -100
            }
          ]
        }
      ],
      "firstBreakScores": [
        {
          "player": "Davia",
          "score": 1600
        },
        {
          "player": "Ellen",
          "score": 1000
        },
        {
          "player": "Rick",
          "score": 100
        }
      ],
      "endOfRoundScores": [
        {
          "player": "Davia",
          "score": 2100
        },
        {
          "player": "Ellen",
          "score": 4200
        },
        {
          "player": "Rick",
          "score": -100
        }
      ]
    },
    "doubleJeopardy": {
      "categories": [
        "U.S. PRESIDENTS",
        "ARCHITECTURE",
        "POTENT POTABLES",
        "BEST PICTURES",
        "GEOGRAPHY",
        "PLAYWRIGHTS"
      ],
      "clues": [
        {
          "category": "U.S. PRESIDENTS",
          "value": 200,
          "clue": "He not only founded the University of Virginia, he also chose its first professors",
          "answer": "Thomas Jefferson",
          "isDailyDouble": false,
          "orderNumber": 1,
          "correctContestants": [],
          "incorrectContestants": [],
          "wasTripleStumper": false,
          "runningScores": [
            {
              "player": "Davia",
              "score": 2100
            },
            {
              "player": "Ellen",
              "score": 4400
            },
            {
              "player": "Rick",
              "score": -100
            }
          ]
        },
        {
          "category": "POTENT POTABLES",
          "value": 200,
          "clue": "Perrier-Jouet's Belle Epoque brand of this sparkling wine comes in a special painted bottle",
          "answer": "champagne",
          "isDailyDouble": false,
          "orderNumber": 2,
          "correctContestants": [],
          "incorrectContestants": [],
          "wasTripleStumper": false,
          "runningScores": [
            {
              "player": "Davia",
              "score": 2300
            },
            {
              "player": "Ellen",
              "score": 4400
            },
            {
              "player": "Rick",
              "score": -100
            }
          ]
        },
        {
          "category": "U.S. PRESIDENTS",
          "value": 400,
          "clue": "At 5' 6\" he was nicknamed \"Little Van\"",
          "answer": "Van Buren",
          "isDailyDouble": false,
          "orderNumber": 3,
          "correctContestants": [],
          "incorrectContestants": [],
          "wasTripleStumper": false,
          "runningScores": [
            {
              "player": "Davia",
              "score": 2300
            },
            {
              "player": "Ellen",
              "score": 4800
            },
            {
              "player": "Rick",
              "score": -100
            }
          ]
        },
        {
          "category": "U.S. PRESIDENTS",
          "value": 600,
          "clue": "In 1906 he became the first president & the first American to win a Nobel Prize",
          "answer": "Teddy Roosevelt",
          "isDailyDouble": false,
          "orderNumber": 4,
          "correctContestants": [],
          "incorrectContestants": [],
          "wasTripleStumper": false,
          "runningScores": [
            {
              "player": "Davia",
              "score": 2900
            },
            {
              "player": "Ellen",
              "score": 4800
            },
            {
              "player": "Rick",
              "score": -100
            }
          ]
        },
        {
          "category": "U.S. PRESIDENTS",
          "value": 800,
          "clue": "In 1849, less than a week before his death, this first \"dark horse\" president was baptized",
          "answer": "Polk",
          "isDailyDouble": false,
          "orderNumber": 5,
          "correctContestants": [],
          "incorrectContestants": [],
          "wasTripleStumper": false,
          "runningScores": [
            {
              "player": "Davia",
              "score": 3700
            },
            {
              "player": "Ellen",
              "score": 4800
            },
            {
              "player": "Rick",
              "score": -100
            }
          ]
        },
        {
          "category": "U.S. PRESIDENTS",
          "value": 1000,
          "clue": "The Cincinnati home of this President & Chief Justice is now a national historic site",
          "answer": "Taft",
          "isDailyDouble": false,
          "orderNumber": 6,
          "correctContestants": [],
          "incorrectContestants": [],
          "wasTripleStumper": false,
          "runningScores": [
            {
              "player": "Davia",
              "score": 4700
            },
            {
              "player": "Ellen",
              "score": 4800
            },
            {
              "player": "Rick",
              "score": -100
            }
          ]
        },
        {
          "category": "BEST PICTURES",
          "value": 200,
          "clue": "Mel Gibson used members of the Irish army for the battle scenes in this Best Picture of 1995",
          "answer": "Braveheart",
          "isDailyDouble": false,
          "orderNumber": 7,
          "correctContestants": [],
          "incorrectContestants": [],
          "wasTripleStumper": false,
          "runningScores": [
            {
              "player": "Davia",
              "score": 4900
            },
            {
              "player": "Ellen",
              "score": 4800
            },
            {
              "player": "Rick",
              "score": -100
            }
          ]
        },
        {
          "category": "BEST PICTURES",
          "value": 400,
          "clue": "This movie taught us that life is like a box of chocolates...you never know what you're gonna get",
          "answer": "Forrest Gump",
          "isDailyDouble": false,
          "orderNumber": 8,
          "correctContestants": [],
          "incorrectContestants": [],
          "wasTripleStumper": false,
          "runningScores": [
            {
              "player": "Davia",
              "score": 5300
            },
            {
              "player": "Ellen",
              "score": 4800
            },
            {
              "player": "Rick",
              "score": -100
            }
          ]
        },
        {
          "category": "BEST PICTURES",
          "value": 600,
          "clue": "This 1941 Best Picture centered on a Welsh mining family",
          "answer": "How Green Was My Valley",
          "isDailyDouble": false,
          "orderNumber": 9,
          "correctContestants": [],
          "incorrectContestants": [],
          "wasTripleStumper": false,
          "runningScores": [
            {
              "player": "Davia",
              "score": 5300
            },
            {
              "player": "Ellen",
              "score": 4200
            },
            {
              "player": "Rick",
              "score": 500
            }
          ]
        },
        {
          "category": "BEST PICTURES",
          "value": 500,
          "clue": "\"Consider yourself\" smart if you know it won Best Picture of 1968",
          "answer": "Oliver",
          "isDailyDouble": true,
          "orderNumber": 10,
          "correctContestants": [],
          "incorrectContestants": [],
          "wasTripleStumper": false,
          "runningScores": [
            {
              "player": "Davia",
              "score": 5300
            },
            {
              "player": "Ellen",
              "score": 4200
            },
            {
              "player": "Rick",
              "score": 0
            }
          ]
        },
        {
          "category": "BEST PICTURES",
          "value": 1000,
          "clue": "Based on an Edna Ferber novel, it was the first western to win the award",
          "answer": "Cimarron",
          "isDailyDouble": false,
          "orderNumber": 11,
          "correctContestants": [],
          "incorrectContestants": [],
          "wasTripleStumper": true,
          "runningScores": [
            {
              "player": "Davia",
              "score": 5300
            },
            {
              "player": "Ellen",
              "score": 4200
            },
            {
              "player": "Rick",
              "score": 0
            }
          ]
        },
        {
          "category": "POTENT POTABLES",
          "value": 400,
          "clue": "As many as 40 herbs & flavorings go into this wine-based martini ingredient",
          "answer": "vermouth",
          "isDailyDouble": false,
          "orderNumber": 12,
          "correctContestants": [],
          "incorrectContestants": [],
          "wasTripleStumper": false,
          "runningScores": [
            {
              "player": "Davia",
              "score": 5300
            },
            {
              "player": "Ellen",
              "score": 4600
            },
            {
              "player": "Rick",
              "score": 0
            }
          ]
        },
        {
          "category": "POTENT POTABLES",
          "value": 600,
          "clue": "The name of mead goes back to madhu, the Sanskrit word for this mead ingredient",
          "answer": "honey",
          "isDailyDouble": false,
          "orderNumber": 13,
          "correctContestants": [],
          "incorrectContestants": [],
          "wasTripleStumper": false,
          "runningScores": [
            {
              "player": "Davia",
              "score": 5300
            },
            {
              "player": "Ellen",
              "score": 4600
            },
            {
              "player": "Rick",
              "score": 600
            }
          ]
        },
        {
          "category": "POTENT POTABLES",
          "value": 800,
          "clue": "This country makes retsina as welll as mastika, a gin-like drink flavored with resin",
          "answer": "Greece",
          "isDailyDouble": false,
          "orderNumber": 14,
          "correctContestants": [],
          "incorrectContestants": [],
          "wasTripleStumper": false,
          "runningScores": [
            {
              "player": "Davia",
              "score": 5300
            },
            {
              "player": "Ellen",
              "score": 5400
            },
            {
              "player": "Rick",
              "score": 600
            }
          ]
        },
        {
          "category": "POTENT POTABLES",
          "value": 1000,
          "clue": "Alborg on the Jutland peninsula is a center for the manufacture of this spirit, Denmark's national drink",
          "answer": "aquavit",
          "isDailyDouble": false,
          "orderNumber": 15,
          "correctContestants": [],
          "incorrectContestants": [],
          "wasTripleStumper": false,
          "runningScores": [
            {
              "player": "Davia",
              "score": 5300
            },
            {
              "player": "Ellen",
              "score": 5400
            },
            {
              "player": "Rick",
              "score": 1600
            }
          ]
        },
        {
          "category": "ARCHITECTURE",
          "value": 200,
          "clue": "Michael Graves' Dolphin Hotel at this Florida theme park is topped with 2 55'-high dolphin sculptures",
          "answer": "Walt Disney World",
          "isDailyDouble": false,
          "orderNumber": 16,
          "correctContestants": [],
          "incorrectContestants": [],
          "wasTripleStumper": false,
          "runningScores": [
            {
              "player": "Davia",
              "score": 5500
            },
            {
              "player": "Ellen",
              "score": 5200
            },
            {
              "player": "Rick",
              "score": 1600
            }
          ]
        },
        {
          "category": "GEOGRAPHY",
          "value": 200,
          "clue": "Ben Nevis, the highest mountain in Great Britain, is located in this country",
          "answer": "Scotland",
          "isDailyDouble": false,
          "orderNumber": 17,
          "correctContestants": [],
          "incorrectContestants": [],
          "wasTripleStumper": false,
          "runningScores": [
            {
              "player": "Davia",
              "score": 5500
            },
            {
              "player": "Ellen",
              "score": 5400
            },
            {
              "player": "Rick",
              "score": 1400
            }
          ]
        },
        {
          "category": "PLAYWRIGHTS",
          "value": 200,
          "clue": "This \"Pygmalion\" author wrote his 1913 play \"Great Catherine\" for actress Gertrude Kingston",
          "answer": "Shaw",
          "isDailyDouble": false,
          "orderNumber": 18,
          "correctContestants": [],
          "incorrectContestants": [],
          "wasTripleStumper": false,
          "runningScores": [
            {
              "player": "Davia",
              "score": 5700
            },
            {
              "player": "Ellen",
              "score": 5400
            },
            {
              "player": "Rick",
              "score": 1400
            }
          ]
        },
        {
          "category": "GEOGRAPHY",
          "value": 400,
          "clue": "Of the 10 longest rivers in the world, 1 of the 3 that flow into the Atlantic",
          "answer": "Amazon, Congo, Parana",
          "isDailyDouble": false,
          "orderNumber": 19,
          "correctContestants": [],
          "incorrectContestants": [],
          "wasTripleStumper": true,
          "runningScores": [
            {
              "player": "Davia",
              "score": 5700
            },
            {
              "player": "Ellen",
              "score": 5400
            },
            {
              "player": "Rick",
              "score": 1400
            }
          ]
        },
        {
          "category": "GEOGRAPHY",
          "value": 600,
          "clue": "Bratislava, Belgrade & Budapest all lie on this river",
          "answer": "Danube",
          "isDailyDouble": false,
          "orderNumber": 20,
          "correctContestants": [],
          "incorrectContestants": [],
          "wasTripleStumper": false,
          "runningScores": [
            {
              "player": "Davia",
              "score": 6300
            },
            {
              "player": "Ellen",
              "score": 5400
            },
            {
              "player": "Rick",
              "score": 1400
            }
          ]
        },
        {
          "category": "GEOGRAPHY",
          "value": 800,
          "clue": "A breed of sheep is named for this range of hills in western England known for it beautiful villages",
          "answer": "cotswold",
          "isDailyDouble": false,
          "orderNumber": 21,
          "correctContestants": [],
          "incorrectContestants": [],
          "wasTripleStumper": false,
          "runningScores": [
            {
              "player": "Davia",
              "score": 6300
            },
            {
              "player": "Ellen",
              "score": 6200
            },
            {
              "player": "Rick",
              "score": 1400
            }
          ]
        },
        {
          "category": "GEOGRAPHY",
          "value": 1000,
          "clue": "Swaziland is bounded on one side by Mozambique & on 3 sides by this country",
          "answer": "South Africa",
          "isDailyDouble": true,
          "orderNumber": 22,
          "correctContestants": [],
          "incorrectContestants": [],
          "wasTripleStumper": false,
          "runningScores": [
            {
              "player": "Davia",
              "score": 6300
            },
            {
              "player": "Ellen",
              "score": 7200
            },
            {
              "player": "Rick",
              "score": 1400
            }
          ]
        },
        {
          "category": "PLAYWRIGHTS",
          "value": 400,
          "clue": "Plautus was the leading comic playwright of this ancient empire",
          "answer": "Roman empire",
          "isDailyDouble": false,
          "orderNumber": 23,
          "correctContestants": [],
          "incorrectContestants": [],
          "wasTripleStumper": false,
          "runningScores": [
            {
              "player": "Davia",
              "score": 6300
            },
            {
              "player": "Ellen",
              "score": 7600
            },
            {
              "player": "Rick",
              "score": 1400
            }
          ]
        },
        {
          "category": "PLAYWRIGHTS",
          "value": 600,
          "clue": "His comedy \"The Star-Spangled Girl\" is set in a duplex apartment overlooking San Francisco Bay",
          "answer": "Neil Simon",
          "isDailyDouble": false,
          "orderNumber": 24,
          "correctContestants": [],
          "incorrectContestants": [],
          "wasTripleStumper": false,
          "runningScores": [
            {
              "player": "Davia",
              "score": 6900
            },
            {
              "player": "Ellen",
              "score": 7600
            },
            {
              "player": "Rick",
              "score": 1400
            }
          ]
        },
        {
          "category": "PLAYWRIGHTS",
          "value": 800,
          "clue": "This Swede satirized Stockholm society in his first novel, \"The Red Room\", published in 1879",
          "answer": "Strindberg",
          "isDailyDouble": false,
          "orderNumber": 25,
          "correctContestants": [],
          "incorrectContestants": [],
          "wasTripleStumper": false,
          "runningScores": [
            {
              "player": "Davia",
              "score": 7700
            },
            {
              "player": "Ellen",
              "score": 7600
            },
            {
              "player": "Rick",
              "score": 600
            }
          ]
        },
        {
          "category": "PLAYWRIGHTS",
          "value": 1000,
          "clue": "\"Lonely people talking to each other can make each other lonelier\", she wrote in \"The Autumn Garden\"",
          "answer": "Lillian Hellman",
          "isDailyDouble": false,
          "orderNumber": 26,
          "correctContestants": [],
          "incorrectContestants": [],
          "wasTripleStumper": true,
          "runningScores": [
            {
              "player": "Davia",
              "score": 7700
            },
            {
              "player": "Ellen",
              "score": 7600
            },
            {
              "player": "Rick",
              "score": 600
            }
          ]
        },
        {
          "category": "ARCHITECTURE",
          "value": 400,
          "clue": "Eliel Saarinen moved to the U.S. after placing second in the competition to design this city's Tribune Tower",
          "answer": "Chicago",
          "isDailyDouble": false,
          "orderNumber": 27,
          "correctContestants": [],
          "incorrectContestants": [],
          "wasTripleStumper": false,
          "runningScores": [
            {
              "player": "Davia",
              "score": 7700
            },
            {
              "player": "Ellen",
              "score": 7600
            },
            {
              "player": "Rick",
              "score": 1000
            }
          ]
        },
        {
          "category": "ARCHITECTURE",
          "value": 600,
          "clue": "Renzo Piano & Richard Rogers designed this Parisian cultural center noted for its controversial industrial style",
          "answer": "Pompidou Center",
          "isDailyDouble": false,
          "orderNumber": 28,
          "correctContestants": [],
          "incorrectContestants": [],
          "wasTripleStumper": false,
          "runningScores": [
            {
              "player": "Davia",
              "score": 7700
            },
            {
              "player": "Ellen",
              "score": 7600
            },
            {
              "player": "Rick",
              "score": 1600
            }
          ]
        },
        {
          "category": "ARCHITECTURE",
          "value": 800,
          "clue": "Designed by Johnson & Burgee, this glass church in Calif. is higher & wider inside than Notre Dame",
          "answer": "Crystal Cathedral",
          "isDailyDouble": false,
          "orderNumber": 29,
          "correctContestants": [],
          "incorrectContestants": [],
          "wasTripleStumper": false,
          "runningScores": [
            {
              "player": "Davia",
              "score": 7700
            },
            {
              "player": "Ellen",
              "score": 7600
            },
            {
              "player": "Rick",
              "score": 2400
            }
          ]
        },
        {
          "category": "ARCHITECTURE",
          "value": 1000,
          "clue": "Built in 1968, this architect's New National Gallery in West Berlin exemplifies his \"less is more\" style",
          "answer": "Mies van der Rohe",
          "isDailyDouble": false,
          "orderNumber": 30,
          "correctContestants": [],
          "incorrectContestants": [],
          "wasTripleStumper": true,
          "runningScores": [
            {
              "player": "Davia",
              "score": 7700
            },
            {
              "player": "Ellen",
              "score": 7600
            },
            {
              "player": "Rick",
              "score": 2400
            }
          ]
        }
      ],
      "endOfRoundScores": [
        {
          "player": "Davia",
          "score": 7700
        },
        {
          "player": "Ellen",
          "score": 7600
        },
        {
          "player": "Rick",
          "score": 2400
        }
      ]
    },
    "finalJeopardy": {
      "category": "THE NEW TESTAMENT",
      "clue": "Called the church's first theologian, a quarter of the books in the New Testament are credited to him",
      "answer": "Paul",
      "responses": [
        {
          "contestant": "Rick",
          "response": "Who was Paul",
          "isCorrect": true,
          "isIncorrect": false,
          "value": 100,
          "finalScore": 2500
        },
        {
          "contestant": "Ellen",
          "response": "Who was Peter?",
          "isCorrect": false,
          "isIncorrect": true,
          "value": 2799,
          "finalScore": 4801
        },
        {
          "contestant": "Davia",
          "response": "Who is Paul?",
          "isCorrect": true,
          "isIncorrect": false,
          "value": 2899,
          "finalScore": 10599
        }
      ]
    }
  },
  "finalScores": [
    {
      "player": "Davia",
      "score": "$10,599"
    },
    {
      "player": "Ellen",
      "score": "$4,801"
    },
    {
      "player": "Rick",
      "score": "$2,500"
    }
  ],
  "coryatScores": [
    {
      "player": "Davia",
      "score": 7700
    },
    {
      "player": "Ellen",
      "score": 7300
    },
    {
      "player": "Rick",
      "score": 2900
    }
  ]
}